cline_core/__init__.py
cline_core/cline_instance.py
cline_core/py.typed
cline_core/proto/cline/account_pb2.py
cline_core/proto/cline/account_pb2_grpc.py
cline_core/proto/cline/browser_pb2.py
cline_core/proto/cline/browser_pb2_grpc.py
cline_core/proto/cline/checkpoints_pb2.py
cline_core/proto/cline/checkpoints_pb2_grpc.py
cline_core/proto/cline/commands_pb2.py
cline_core/proto/cline/commands_pb2_grpc.py
cline_core/proto/cline/common_pb2.py
cline_core/proto/cline/common_pb2_grpc.py
cline_core/proto/cline/dictation_pb2.py
cline_core/proto/cline/dictation_pb2_grpc.py
cline_core/proto/cline/file_pb2.py
cline_core/proto/cline/file_pb2_grpc.py
cline_core/proto/cline/hooks_pb2.py
cline_core/proto/cline/hooks_pb2_grpc.py
cline_core/proto/cline/mcp_pb2.py
cline_core/proto/cline/mcp_pb2_grpc.py
cline_core/proto/cline/models_pb2.py
cline_core/proto/cline/models_pb2_grpc.py
cline_core/proto/cline/oca_account_pb2.py
cline_core/proto/cline/oca_account_pb2_grpc.py
cline_core/proto/cline/slash_pb2.py
cline_core/proto/cline/slash_pb2_grpc.py
cline_core/proto/cline/state_pb2.py
cline_core/proto/cline/state_pb2_grpc.py
cline_core/proto/cline/task_pb2.py
cline_core/proto/cline/task_pb2_grpc.py
cline_core/proto/cline/ui_pb2.py
cline_core/proto/cline/ui_pb2_grpc.py
cline_core/proto/cline/web_pb2.py
cline_core/proto/cline/web_pb2_grpc.py
cline_core/proto/host/diff_pb2.py
cline_core/proto/host/diff_pb2_grpc.py
cline_core/proto/host/env_pb2.py
cline_core/proto/host/env_pb2_grpc.py
cline_core/proto/host/testing_pb2.py
cline_core/proto/host/testing_pb2_grpc.py
cline_core/proto/host/window_pb2.py
cline_core/proto/host/window_pb2_grpc.py
cline_core/proto/host/workspace_pb2.py
cline_core/proto/host/workspace_pb2_grpc.py
cline_core-0.1.10.dist-info/METADATA
cline_core-0.1.10.dist-info/WHEEL
cline_core-0.1.10.dist-info/top_level.txt
cline_core-0.1.10.dist-info/RECORD
