Metadata-Version: 2.4
Name: cline-core
Version: 0.1.10
Summary: Add your description here
Author-email: Adem Gaygusuz <adem@ardweb.co.uk>
Requires-Python: >=3.10
